agora/__init__.py
agora/commod/__init__.py
agora/commod/timeseries.py
agora/commod/ufo_commod_asset.py
agora/commod/ufo_commod_contract.py
agora/commod/ufo_commod_forward.py
agora/commod/ufo_commod_futures.py
agora/commod/ufo_commod_nrby.py
agora/commod/ufo_commod_swap.py
agora/commod/test/__init__.py
agora/commod/test/test_ufo_commod_contract.py
agora/commod/test/test_ufo_commod_futures.py
agora/econometrics/__init__.py
agora/econometrics/arma_functions.py
agora/econometrics/gbm_functions.py
agora/econometrics/regression.py
agora/equity/__init__.py
agora/equity/ufo_cash_dividend.py
agora/equity/ufo_corporate_actions.py
agora/equity/ufo_depositary_receipt.py
agora/equity/ufo_equity_asset.py
agora/equity/ufo_equity_cash.py
agora/equity/ufo_equity_cfd.py
agora/equity/ufo_equity_index.py
agora/equity/ufo_equity_index_contract.py
agora/equity/ufo_equity_index_futures.py
agora/equity/ufo_equity_pair.py
agora/equity/ufo_equity_vol_matrix.py
agora/equity/test/__init__.py
agora/equity/test/test_ufo_equity_asset.py
agora/equity/test/test_ufo_equity_cash.py
agora/equity/test/test_ufo_equity_cfd.py
agora/equity/test/test_ufo_equity_index.py
agora/equity/test/test_ufo_equity_index_contract.py
agora/equity/test/test_ufo_equity_index_futures.py
agora/equity/test/test_ufo_equity_pair.py
agora/fixed_income/__init__.py
agora/fixed_income/ufo_fixed_income.py
agora/system/__init__.py
agora/system/ageing_api.py
agora/system/price_curves_api.py
agora/system/risk_decorators.py
agora/system/tradable_api.py
agora/system/trade_api.py
agora/system/transaction_api.py
agora/system/ufo_amortized_cash.py
agora/system/ufo_asset.py
agora/system/ufo_book.py
agora/system/ufo_broker.py
agora/system/ufo_cash_balance.py
agora/system/ufo_category.py
agora/system/ufo_cfd_fixed_leg.py
agora/system/ufo_cfd_floating_leg.py
agora/system/ufo_container.py
agora/system/ufo_currency.py
agora/system/ufo_currency_cross.py
agora/system/ufo_database.py
agora/system/ufo_exchange.py
agora/system/ufo_forward_cash.py
agora-1.2.3.dist-info/LICENSE.txt
agora-1.2.3.dist-info/METADATA
agora-1.2.3.dist-info/WHEEL
agora-1.2.3.dist-info/top_level.txt
agora-1.2.3.dist-info/RECORD
